blueforge/__init__.py
blueforge/api.py
blueforge/bigquery.py
blueforge/data_set.py
blueforge/s3.py
blueforge/3rd/__init__.py
blueforge/3rd/bigquery.py
blueforge/3rd/messenger.py
blueforge/3rd/s3.py
blueforge/apis/__init__.py
blueforge/apis/bigquery.py
blueforge/apis/s3.py
blueforge/apis/facebook/__init__.py
blueforge/apis/facebook/attachments.py
blueforge/apis/facebook/buttons.py
blueforge/apis/facebook/elements.py
blueforge/apis/facebook/message.py
blueforge/apis/facebook/quick_reply.py
blueforge/apis/facebook/template.py
blueforge/apis/telegram/__init__.py
blueforge/apis/telegram/edit.py
blueforge/apis/telegram/markup.py
blueforge/apis/telegram/message.py
blueforge/core/__init__.py
blueforge/core/exceptions.py
blueforge/data/whatsit/2017-10-07/api.json
blueforge/util/__init__.py
blueforge/util/config.py
blueforge/util/data_set.py
blueforge/util/file.py
blueforge/util/trans.py
blueforge-0.1.118.dist-info/DESCRIPTION.rst
blueforge-0.1.118.dist-info/METADATA
blueforge-0.1.118.dist-info/RECORD
blueforge-0.1.118.dist-info/WHEEL
blueforge-0.1.118.dist-info/metadata.json
blueforge-0.1.118.dist-info/top_level.txt
