Metadata-Version: 2.0
Name: blueforge
Version: 0.1.118
Summary: The Blueforge for Python
Home-page: https://github.com/BlueHack-Core/blueforge
Author: Bluehack
Author-email: jh.lim@bluehack.net
License: MIT
Platform: UNKNOWN
Classifier: License :: OSI Approved :: MIT License
Classifier: Programming Language :: Python
Classifier: Programming Language :: Python :: 3.6
Classifier: Development Status :: 1 - Planning
Requires-Dist: boto3 (>=1.4.7)
Requires-Dist: requests (>=2.18.4)
Requires-Dist: google-cloud-bigquery (>=0.27.0)
